qctic/__init__.py
qctic/__version__.py
qctic/api.py
qctic/backend.py
qctic/cli.py
qctic/job.py
qctic/provider.py
qctic/schemas.py
qctic/utils.py
tests/__init__.py
tests/conftest.py
tests/test_api.py
tests/test_backends.py
tests/test_provider.py
tests/test_schemas.py
tests/test_utils.py
tests/utils.py
qctic-0.18.3.dist-info/METADATA
qctic-0.18.3.dist-info/WHEEL
qctic-0.18.3.dist-info/entry_points.txt
qctic-0.18.3.dist-info/top_level.txt
qctic-0.18.3.dist-info/RECORD
