Metadata-Version: 2.1
Name: qctic
Version: 0.18.3
Summary: Qiskit provider to interact with the QCTIC quantum simulator platform
Home-page: https://bitbucket.org/fundacionctic/erwin-qiskit
Author: Andres Garcia Mangas
Author-email: andres.garcia@fundacionctic.org
License: UNKNOWN
Keywords: quantum simulator qiskit
Platform: UNKNOWN
Classifier: Programming Language :: Python :: 3.6
Classifier: Programming Language :: Python :: 3.7
Classifier: Programming Language :: Python :: 3.8
Classifier: Programming Language :: Python :: 3.9
Classifier: License :: OSI Approved :: MIT License
Requires-Python: >=3.6
Requires-Dist: qiskit (<0.26,>=0.25)
Requires-Dist: marshmallow (<4.0,>=3.0)
Requires-Dist: tornado (<7.0,>=6.0)
Requires-Dist: numpy (<=1.20.1,>=1.17)
Requires-Dist: scipy (<=1.6.1,>=1.4)
Requires-Dist: sympy (<=1.7.1,>=1.3)
Provides-Extra: dev
Requires-Dist: autopep8 (<2.0,>=1.5) ; extra == 'dev'
Requires-Dist: pylint (<3.0,>=2.0) ; extra == 'dev'
Requires-Dist: rope (<1.0,>=0.16.0) ; extra == 'dev'
Requires-Dist: pytest (<6.0,>=5.0) ; extra == 'dev'
Requires-Dist: bumpversion (<1.0,>=0.5.3) ; extra == 'dev'
Requires-Dist: pytest-httpserver (<2.0,>=1.0) ; extra == 'dev'
Requires-Dist: coloredlogs (<15.0,>=14.0) ; extra == 'dev'
Requires-Dist: pytest-cov (<3.0,>=2.8.1) ; extra == 'dev'
Requires-Dist: pytest-asyncio (<1.0,>=0.10.0) ; extra == 'dev'
Requires-Dist: notebook (<7.0,>=6.0) ; extra == 'dev'
Provides-Extra: nest
Requires-Dist: nest-asyncio (<2.0,>=1.4.0) ; extra == 'nest'
